dltools/version.py
dltools/hittype.cpython-37m-x86_64-linux-gnu.so
dltools/__init__.py
dltools/hittype_spark.py
dltools/lmafmt.cpython-37m-x86_64-linux-gnu.so
dltools/lmffmt.py
dltools/dummy/io_spark.py
dltools/dummy/__init__.py
dltools/sp8/io_spark.py
dltools/sp8/__init__.py
dltools/cov/generic.py
dltools/cov/inpools.py
dltools/cov/complicated.py
dltools/cov/core.py
dltools/cov/__init__.py
dltools/cov/inapool.py
dltools/cov/markup.py
dltools/cov/simple.py
dltools/sacla/model.cpython-37m-x86_64-linux-gnu.so
dltools/sacla/io_spark.py
dltools/sacla/__init__.py
dltools-201910.1.dist-info/top_level.txt
dltools-201910.1.dist-info/METADATA
dltools-201910.1.dist-info/WHEEL
dltools-201910.1.dist-info/RECORD
