Metadata-Version: 2.1
Name: dltools
Version: 201910.1
Summary: UNKNOWN
Home-page: https://github.com/DaehyunPY/dltools
Author: Daehyun You
Author-email: daehyun@dc.tohoku.ac.jp
License: MIT
Platform: UNKNOWN
Requires-Dist: numba
Requires-Dist: numpy
Requires-Dist: pyspark
Requires-Dist: cytoolz
